edx_theme/__init__.py
edx_theme/breadcrumbs.html
edx_theme/footer.html
edx_theme/layout.html
edx_theme/layout_old.html
edx_theme/search.html
edx_theme/searchbox.html
edx_theme/theme.conf
edx_theme/versions.html
edx_theme/static/css/badge_only.css
edx_theme/static/css/edx-logo-header.png
edx_theme/static/css/favicon.ico
edx_theme/static/css/theme.css
edx_theme/static/font/fontawesome_webfont.eot
edx_theme/static/font/fontawesome_webfont.svg
edx_theme/static/font/fontawesome_webfont.ttf
edx_theme/static/font/fontawesome_webfont.woff
edx_theme/static/js/theme.js
edx_sphinx_theme-3.1.0.dist-info/AUTHORS
edx_sphinx_theme-3.1.0.dist-info/LICENSE.txt
edx_sphinx_theme-3.1.0.dist-info/METADATA
edx_sphinx_theme-3.1.0.dist-info/WHEEL
edx_sphinx_theme-3.1.0.dist-info/top_level.txt
edx_sphinx_theme-3.1.0.dist-info/RECORD
