Metadata-Version: 2.1
Name: edx-sphinx-theme
Version: 3.1.0
Summary: A Sphinx theme for Open edX documentation
Home-page: https://github.com/openedx/edx-sphinx-theme
Author: edX
Author-email: oscm@edx.org
License: Apache Software License 2.0
Keywords: Sphinx edx
Platform: UNKNOWN
Classifier: Development Status :: 4 - Beta
Classifier: Framework :: Sphinx :: Theme
Classifier: Intended Audience :: Developers
Classifier: License :: OSI Approved :: Apache Software License
Classifier: Natural Language :: English
Classifier: Programming Language :: Python :: 3
Classifier: Programming Language :: Python :: 3.8
License-File: LICENSE.txt
License-File: AUTHORS
Requires-Dist: Sphinx (<6.0.0)
Requires-Dist: six
